parseaia/__init__.py
parseaia/__main__.py
parseaia/codeclasses.py
parseaia/dictionaryutils.py
parseaia/funcs.py
parseaia/main.py
parseaia/otherclasses.py
parseaia/uiclasses.py
parseaia-0.3.7.dist-info/LICENSE
parseaia-0.3.7.dist-info/METADATA
parseaia-0.3.7.dist-info/WHEEL
parseaia-0.3.7.dist-info/top_level.txt
parseaia-0.3.7.dist-info/RECORD
