Metadata-Version: 2.1
Name: parseaia
Version: 0.3.7
Summary: A package for reading .aia files from App Inventor
Home-page: https://github.com/PolarsBear/parseaia
Author: Lars Von Wangenheim
Author-email: larzitovw@gmail.com
License: UNKNOWN
Project-URL: Bug Tracker, https://github.com/PolarsBear/parseaia/issues
Platform: UNKNOWN
Classifier: Programming Language :: Python :: 3
Classifier: License :: OSI Approved :: MIT License
Classifier: Operating System :: OS Independent
Requires-Python: >=3.6
License-File: LICENSE
Requires-Dist: xmltodict
Requires-Dist: Pillow
Requires-Dist: mutagen
